setup.py
prototyping/__init__.py
prototyping.egg-info/PKG-INFO
prototyping.egg-info/SOURCES.txt
prototyping.egg-info/dependency_links.txt
prototyping.egg-info/top_level.txt