Metadata-Version: 1.1
Name: prototyping
Version: 0.1.0
Summary: Language tools for fast development and debugging.
Home-page: http://github.com/danijar/prototyping
Author: UNKNOWN
Author-email: UNKNOWN
License: Apache 2.0
Platform: UNKNOWN
Classifier: Programming Language :: Python :: 3
Classifier: License :: OSI Approved :: Apache Software License
Classifier: Intended Audience :: Science/Research
